<?xml version="1.0" encoding="UTF-8"?>
<nomenclatures xmlns="http://www.ekylibre.org/XML/2013/nomenclatures">
  <nomenclature name="abilities">
    <property-natures>
      <property-nature name="parameters" type="list" choices="variety, issue_nature" required="false"/>
    </property-natures>
    <items>
      <!--
          Abilities are ACTIVE (not PASSIVE)
          Example: Product can do something awesome
      -->
      <item name="consume"    parameters="variety"/>
      <item name="produce"    parameters="variety"/>
      <item name="kill"       parameters="variety"/>
      <item name="grind"      parameters="variety"/>
      <item name="administer_care" parameters="variety"/>
      <item name="care"       parameters="variety"/>
      <item name="drive"      parameters="variety"/>
      <item name="manage"     parameters="variety"/> <!-- ? -->
      <item name="feed"       parameters="variety"/>
      <item name="fertilize"/>
      <item name="catch"      parameters="variety"/>
      <item name="spread"     parameters="variety"/>
      <item name="spray"/>
      <!-- Soil working  -->
      <item name="plow"/>
      <item name="plow_superficially"/>
      <item name="hoe"/>
      <item name="uncompact"/>
      <item name="clean"      parameters="variety"/>
      <item name="sow"/>
      <item name="implant"/>
      <item name="grow"/>
      <item name="mow"/>
      <item name="bunch"/>
      <item name="rake"       parameters="variety"/>
      <item name="harvest"    parameters="variety"/>
      <item name="pick"       parameters="variety"/>
      <item name="move"/>
      <item name="enclose"/> <!-- clôturer des champs  -->
      <!-- inplanting  -->
      <item name="wrap"       parameters="variety"/>
      <item name="seat"       parameters="variety"/>
      <!-- store matter  -->
      <item name="store"      parameters="variety"/>
      <item name="store_fluid"/>
      <item name="store_liquid"/>
      <item name="store_gaz"/>
      <!-- store matter  -->
      <item name="milk"       parameters="variety"/>
      <item name="tow"        parameters="variety"/>
      <item name="cut"/>
      <item name="deliver"    parameters="variety"/>
      <item name="freeze"/>
      <item name="blow"/>
      <item name="repair"     parameters="variety"/>
      <item name="lubricate"  parameters="variety"/>
      <item name="press"      parameters="variety"/>
      <!-- Wine making  -->
      <item name="chaptelise" parameters="variety"/>
      <item name="sulfurize"  parameters="variety"/>
      <item name="fermentize" parameters="variety"/>
      <item name="catalyze"   parameters="variety"/>
      <item name="acidify"    parameters="variety"/>
      <item name="alkalinize" parameters="variety"/>
      <item name="clarify"    parameters="variety"/>
      <!-- Wine bottling  -->
      <item name="close"      parameters="variety"/>
      <item name="fill"       parameters="variety"/>
      <!-- Animal reproduction  -->
      <item name="administer_inseminate" parameters="variety"/>
      <item name="inseminate" parameters="variety"/>
    </items>
  </nomenclature>
</nomenclatures>
