<?xml version="1.0" encoding="UTF-8"?>
<nomenclatures xmlns="http://www.ekylibre.org/XML/2013/nomenclatures">
  <nomenclature name="administrative_areas">
    <property-natures>
      <property-nature name="nature"  type="choice" nomenclature="administrative_area_natures" requied="true"/>
      <property-nature name="code"    type="string"/> <!-- Code ISO 3166-2 if exists-->
      <property-nature name="parent"  type="choice" nomenclature="administrative_areas"/>
    </property-natures>
    <items>
      <!-- French regions -->
      <item name="france_region_alsace"                     code="FR-A"  nature="france_region"/>
      <item name="france_region_aquitaine"                  code="FR-B"  nature="france_region"/>
      <item name="france_region_auvergne"                   code="FR-C"  nature="france_region"/>
      <item name="france_region_basse_normandie"            code="FR-P"  nature="france_region"/>
      <item name="france_region_bourgogne"                  code="FR-D"  nature="france_region"/>
      <item name="france_region_bretagne"                   code="FR-E"  nature="france_region"/>
      <item name="france_region_centre"                     code="FR-F"  nature="france_region"/>
      <item name="france_region_champagne_ardenne"          code="FR-G"  nature="france_region"/>
      <item name="france_region_corse"                      code="FR-H"  nature="france_region"/>
      <item name="france_region_franche_comte"              code="FR-I"  nature="france_region"/>
      <item name="france_region_haute_normandie"            code="FR-Q"  nature="france_region"/>
      <item name="france_region_ile_de_france"              code="FR-J"  nature="france_region"/>
      <item name="france_region_languedoc_roussillon"       code="FR-K"  nature="france_region"/>
      <item name="france_region_limousin"                   code="FR-L"  nature="france_region"/>
      <item name="france_region_lorraine"                   code="FR-M"  nature="france_region"/>
      <item name="france_region_midi_pyrenees"              code="FR-N"  nature="france_region"/>
      <item name="france_region_nord_pas_de_calais"         code="FR-O"  nature="france_region"/>
      <item name="france_region_pays_de_la_loire"           code="FR-R"  nature="france_region"/>
      <item name="france_region_picardie"                   code="FR-S"  nature="france_region"/>
      <item name="france_region_poitou_charentes"           code="FR-T"  nature="france_region"/>
      <item name="france_region_provence_alpes_cote_d_azur" code="FR-U"  nature="france_region"/>
      <item name="france_region_rhone_alpes"                code="FR-V"  nature="france_region"/>
      <item name="france_region_guadeloupe"                 code="FR-GP" nature="france_region"/>
      <item name="france_region_guyane"                     code="FR-GF" nature="france_region"/>
      <item name="france_region_martinique"                 code="FR-MQ" nature="france_region"/>
      <item name="france_region_reunion"                    code="FR-RE" nature="france_region"/>
      <item name="france_region_mayotte"                    code="FR-YT" nature="france_region"/>

      <!-- French departments -->
      <item name="france_department_ain"                     code="FR-01" nature="france_department" parent="france_region_rhone_alpes"/>
      <item name="france_department_aisne"                   code="FR-02" nature="france_department" parent="france_region_picardie"/>
      <item name="france_department_allier"                  code="FR-03" nature="france_department" parent="france_region_auvergne"/>
      <item name="france_department_alpes_de_haute_provence" code="FR-04" nature="france_department" parent="france_region_provence_alpes_cote_d_azur"/>
      <item name="france_department_hautes_alpes"            code="FR-05" nature="france_department" parent="france_region_provence_alpes_cote_d_azur"/>
      <item name="france_department_alpes_maritimes"         code="FR-06" nature="france_department" parent="france_region_provence_alpes_cote_d_azur"/>
      <item name="france_department_ardeche"                 code="FR-07" nature="france_department" parent="france_region_rhone_alpes"/>
      <item name="france_department_ardennes"                code="FR-08" nature="france_department" parent="france_region_champagne_ardenne"/>
      <item name="france_department_ariege"                  code="FR-09" nature="france_department" parent="france_region_midi_pyrenees"/>
      <item name="france_department_aube"                    code="FR-10" nature="france_department" parent="france_region_champagne_ardenne"/>
      <item name="france_department_aude"                    code="FR-11" nature="france_department" parent="france_region_languedoc_roussillon"/>
      <item name="france_department_aveyron"                 code="FR-12" nature="france_department" parent="france_region_midi_pyrenees"/>
      <item name="france_department_bouches_du_rhone"        code="FR-13" nature="france_department" parent="france_region_provence_alpes_cote_d_azur"/>
      <item name="france_department_calvados"                code="FR-14" nature="france_department" parent="france_region_basse_normandie"/>
      <item name="france_department_cantal"                  code="FR-15" nature="france_department" parent="france_region_auvergne"/>
      <item name="france_department_charente"                code="FR-16" nature="france_department" parent="france_region_poitou_charentes"/>
      <item name="france_department_charente_maritime"       code="FR-17" nature="france_department" parent="france_region_poitou_charentes"/>
      <item name="france_department_cher"                    code="FR-18" nature="france_department" parent="france_region_centre"/>
      <item name="france_department_correze"                 code="FR-19" nature="france_department" parent="france_region_limousin"/>
      <item name="france_department_corse_du_sud"            code="FR-2A" nature="france_department" parent="france_region_corse"/>
      <item name="france_department_haute_corse"             code="FR-2B" nature="france_department" parent="france_region_corse"/>
      <item name="france_department_cote_d_or"               code="FR-21" nature="france_department" parent="france_region_bourgogne"/>
      <item name="france_department_cotes_d_armor"           code="FR-22" nature="france_department" parent="france_region_bretagne"/>
      <item name="france_department_creuse"                  code="FR-23" nature="france_department" parent="france_region_limousin"/>
      <item name="france_department_dordogne"                code="FR-24" nature="france_department" parent="france_region_aquitaine"/>
      <item name="france_department_doubs"                   code="FR-25" nature="france_department" parent="france_region_franche_comte"/>
      <item name="france_department_drome"                   code="FR-26" nature="france_department" parent="france_region_rhone_alpes"/>
      <item name="france_department_eure"                    code="FR-27" nature="france_department" parent="france_region_haute_normandie"/>
      <item name="france_department_eure_et_loir"            code="FR-28" nature="france_department" parent="france_region_centre"/>
      <item name="france_department_finistere"               code="FR-29" nature="france_department" parent="france_region_bretagne"/>
      <item name="france_department_gard"                    code="FR-30" nature="france_department" parent="france_region_languedoc_roussillon"/>
      <item name="france_department_haute_garonne"           code="FR-31" nature="france_department" parent="france_region_midi_pyrenees"/>
      <item name="france_department_gers"                    code="FR-32" nature="france_department" parent="france_region_midi_pyrenees"/>
      <item name="france_department_gironde"                 code="FR-33" nature="france_department" parent="france_region_aquitaine"/>
      <item name="france_department_herault"                 code="FR-34" nature="france_department" parent="france_region_languedoc_roussillon"/>
      <item name="france_department_ille_et_vilaine"         code="FR-35" nature="france_department" parent="france_region_bretagne"/>
      <item name="france_department_indre"                   code="FR-36" nature="france_department" parent="france_region_centre"/>
      <item name="france_department_indre_et_loire"          code="FR-37" nature="france_department" parent="france_region_centre"/>
      <item name="france_department_isere"                   code="FR-38" nature="france_department" parent="france_region_rhone_alpes"/>
      <item name="france_department_jura"                    code="FR-39" nature="france_department" parent="france_region_franche_comte"/>
      <item name="france_department_landes"                  code="FR-40" nature="france_department" parent="france_region_aquitaine"/>
      <item name="france_department_loir_et_cher"            code="FR-41" nature="france_department" parent="france_region_centre"/>
      <item name="france_department_loire"                   code="FR-42" nature="france_department" parent="france_region_rhone_alpes"/>
      <item name="france_department_haute_loire"             code="FR-43" nature="france_department" parent="france_region_auvergne"/>
      <item name="france_department_loire_atlantique"        code="FR-44" nature="france_department" parent="france_region_pays_de_la_loire"/>
      <item name="france_department_loiret"                  code="FR-45" nature="france_department" parent="france_region_centre"/>
      <item name="france_department_lot"                     code="FR-46" nature="france_department" parent="france_region_midi_pyrenees"/>
      <item name="france_department_lot_et_garonne"          code="FR-47" nature="france_department" parent="france_region_aquitaine"/>
      <item name="france_department_lozere"                  code="FR-48" nature="france_department" parent="france_region_languedoc_roussillon"/>
      <item name="france_department_maine_et_loire"          code="FR-49" nature="france_department" parent="france_region_pays_de_la_loire"/>
      <item name="france_department_manche"                  code="FR-50" nature="france_department" parent="france_region_basse_normandie"/>
      <item name="france_department_marne"                   code="FR-51" nature="france_department" parent="france_region_champagne_ardenne"/>
      <item name="france_department_haute_marne"             code="FR-52" nature="france_department" parent="france_region_champagne_ardenne"/>
      <item name="france_department_mayenne"                 code="FR-53" nature="france_department" parent="france_region_pays_de_la_loire"/>
      <item name="france_department_meurthe_et_moselle"      code="FR-54" nature="france_department" parent="france_region_lorraine"/>
      <item name="france_department_meuse"                   code="FR-55" nature="france_department" parent="france_region_lorraine"/>
      <item name="france_department_morbihan"                code="FR-56" nature="france_department" parent="france_region_bretagne"/>
      <item name="france_department_moselle"                 code="FR-57" nature="france_department" parent="france_region_lorraine"/>
      <item name="france_department_nievre"                  code="FR-58" nature="france_department" parent="france_region_bourgogne"/>
      <item name="france_department_nord"                    code="FR-59" nature="france_department" parent="france_region_nord_pas_de_calais"/>
      <item name="france_department_oise"                    code="FR-60" nature="france_department" parent="france_region_picardie"/>
      <item name="france_department_orne"                    code="FR-61" nature="france_department" parent="france_region_basse_normandie"/>
      <item name="france_department_pas_de_calais"           code="FR-62" nature="france_department" parent="france_region_nord_pas_de_calais"/>
      <item name="france_department_puy_de_dome"             code="FR-63" nature="france_department" parent="france_region_auvergne"/>
      <item name="france_department_pyrenees_atlantiques"    code="FR-64" nature="france_department" parent="france_region_aquitaine"/>
      <item name="france_department_hautes_pyrenees"         code="FR-65" nature="france_department" parent="france_region_midi_pyrenees"/>
      <item name="france_department_pyrenees_orientales"     code="FR-66" nature="france_department" parent="france_region_languedoc_roussillon"/>
      <item name="france_department_bas_rhin"                code="FR-67" nature="france_department" parent="france_region_alsace"/>
      <item name="france_department_haut_rhin"               code="FR-68" nature="france_department" parent="france_region_alsace"/>
      <item name="france_department_rhone"                   code="FR-69" nature="france_department" parent="france_region_rhone_alpes"/>
      <item name="france_department_haute_saone"             code="FR-70" nature="france_department" parent="france_region_franche_comte"/>
      <item name="france_department_saone_et_loire"          code="FR-71" nature="france_department" parent="france_region_bourgogne"/>
      <item name="france_department_sarthe"                  code="FR-72" nature="france_department" parent="france_region_pays_de_la_loire"/>
      <item name="france_department_savoie"                  code="FR-73" nature="france_department" parent="france_region_rhone_alpes"/>
      <item name="france_department_haute_savoie"            code="FR-74" nature="france_department" parent="france_region_rhone_alpes"/>
      <item name="france_department_paris"                   code="FR-75" nature="france_department" parent="france_region_ile_de_france"/>
      <item name="france_department_seine_maritime"          code="FR-76" nature="france_department" parent="france_region_haute_normandie"/>
      <item name="france_department_seine_et_marne"          code="FR-77" nature="france_department" parent="france_region_ile_de_france"/>
      <item name="france_department_yvelines"                code="FR-78" nature="france_department" parent="france_region_ile_de_france"/>
      <item name="france_department_deux_sevres"             code="FR-79" nature="france_department" parent="france_region_poitou_charentes"/>
      <item name="france_department_somme"                   code="FR-80" nature="france_department" parent="france_region_picardie"/>
      <item name="france_department_tarn"                    code="FR-81" nature="france_department" parent="france_region_midi_pyrenees"/>
      <item name="france_department_tarn_et_garonne"         code="FR-82" nature="france_department" parent="france_region_midi_pyrenees"/>
      <item name="france_department_var"                     code="FR-83" nature="france_department" parent="france_region_provence_alpes_cote_d_azur"/>
      <item name="france_department_vaucluse"                code="FR-84" nature="france_department" parent="france_region_provence_alpes_cote_d_azur"/>
      <item name="france_department_vendee"                  code="FR-85" nature="france_department" parent="france_region_pays_de_la_loire"/>
      <item name="france_department_vienne"                  code="FR-86" nature="france_department" parent="france_region_poitou_charentes"/>
      <item name="france_department_haute_vienne"            code="FR-87" nature="france_department" parent="france_region_limousin"/>
      <item name="france_department_vosges"                  code="FR-88" nature="france_department" parent="france_region_lorraine"/>
      <item name="france_department_yonne"                   code="FR-89" nature="france_department" parent="france_region_bourgogne"/>
      <item name="france_department_territoire_de_belfort"   code="FR-90" nature="france_department" parent="france_region_franche_comte"/>
      <item name="france_department_essonne"                 code="FR-91" nature="france_department" parent="france_region_ile_de_france"/>
      <item name="france_department_hauts_de_seine"          code="FR-92" nature="france_department" parent="france_region_ile_de_france"/>
      <item name="france_department_seine_saint_denis"       code="FR-93" nature="france_department" parent="france_region_ile_de_france"/>
      <item name="france_department_val_de_marne"            code="FR-94" nature="france_department" parent="france_region_ile_de_france"/>
      <item name="france_department_val_d_oise"              code="FR-95" nature="france_department" parent="france_region_ile_de_france"/>
      <!-- Do we manage DOM like that ? -->
      <item name="france_department_guadeloupe"              code="FR-GP" nature="france_department" parent="france_region_guadeloupe"/>
      <item name="france_department_guyane"                  code="FR-GF" nature="france_department" parent="france_region_guyane"/>
      <item name="france_department_martinique"              code="FR-MQ" nature="france_department" parent="france_region_martinique"/>
      <item name="france_department_reunion"                 code="FR-RE" nature="france_department" parent="france_region_reunion"/>
      <item name="france_department_mayotte"                 code="FR-YT" nature="france_department" parent="france_region_mayotte"/>

      <!-- French communes -->
    </items>
  </nomenclature>
</nomenclatures>
