<?xml version="1.0" encoding="UTF-8"?>
<nomenclatures xmlns="http://www.ekylibre.org/XML/2013/nomenclatures">
  <nomenclature name="document_natures">
    <property-natures>
      <property-nature name="category" type="list" nomenclature="document_categories"/>
    </property-natures>
    <items>
      <item name="sales_order" category="marketing"/>
      <item name="sales_estimate" category="marketing"/>
      <item name="sales_invoice" category="marketing"/>
      
      <item name="purchases_order" category="exploitation"/>
      <item name="purchases_estimate" category="exploitation"/>
      <item name="purchases_invoice" category="exploitation"/>

      <item name="deposit_list" category="exploitation"/>

      <item name="balance_sheet" category="accountancy"/>
      <item name="income_statement" category="accountancy"/>
      <item name="journal" category="accountancy"/>
      <item name="exchange_accountancy_file_fr" category="accountancy"/>
      <item name="general_journal" category="accountancy"/>
      <item name="general_ledger" category="accountancy"/>
      <item name="trial_balance" category="accountancy"/>
      <item name="tax_assessment" category="accountancy"/>

      <item name="inventory_sheet" category="exploitation"/>
      <item name="stocks" category="exploitation"/>
      <item name="incoming_delivery_docket" category="exploitation"/>
      <item name="outgoing_delivery_docket" category="exploitation"/>
      <item name="outgoing_deliveries_journal" category="exploitation"/>

      <item name="animal_sheet" category="animal_farming"/>
      <item name="animal_list" category="animal_farming"/>
      <item name="animal_husbandry_registry" category="animal_farming"/>

      <item name="prescription" category="health"/>
      <item name="veterinary_booklet" category="health"/>
      
      <item name="manure_management_plan" category="land_parcel_management"/>
      <item name="manure_management_plan_sheet" category="land_parcel_management"/>
      <item name="provisional_manure_management_plan" category="land_parcel_management"/>
      <item name="phytosanitary_registry" category="land_parcel_management"/>
      <item name="land_parcel_registry" category="land_parcel_management"/>
      <item name="vine_phytosanitary_registry" category="land_parcel_management"/>
      
      <item name="phytosanitary_certification" category="land_parcel_management"/>
      <item name="equipment_certification" category="land_parcel_management"/>
      <item name="security_data_sheet" category="land_parcel_management"/>
      
      <item name="activity_cost" category="management"/>
      <item name="intervention_sheet" category="management"/>
      <item name="intervention_registry" category="management"/>

      <item name="wine_detention_registry" category="vinification"/>
      <item name="wine_bottling_registry" category="vinification"/>
      <item name="wine_manipulation_registry" category="vinification"/>

      <item name="entity_sheet" category="exploitation"/>
    </items>
  </nomenclature>
</nomenclatures>
