<?xml version="1.0" encoding="utf-8"?>
<migration name="Add orchard plugin cap varieties">
  <item-creation item="varieties#prunus_armeniaca" parent="prunus" itis_tsn="24769"/>
  <item-creation item="varieties#prunus_armeniaca_abricot_commun_de_clairac" parent="prunus_armeniaca" itis_tsn="24769"/>
  <item-creation item="varieties#prunus_armeniaca_abricot_commun_de_nicole_commerce" parent="prunus_armeniaca" itis_tsn="24769"/>
  <item-creation item="varieties#prunus_armeniaca_abricot_muscat_de_clairac" parent="prunus_armeniaca" itis_tsn="24769"/>
  <item-creation item="varieties#prunus_armeniaca_abricot_nancy_de_clairac" parent="prunus_armeniaca" itis_tsn="24769"/>
  <item-creation item="varieties#prunus_armeniaca_abricot_peche_de_nancy" parent="prunus_armeniaca" itis_tsn="24769"/>
  <item-creation item="varieties#prunus_avium_noire_tardive_a_longue_queue" parent="prunus_avium" itis_tsn="24770"/>
  <item-creation item="varieties#prunus_avium_belle_du_berry_ou_petite_joue_vermeille" parent="prunus_avium" itis_tsn="24770"/>
  <item-creation item="varieties#prunus_avium_blanc_chere" parent="prunus_armeniaca" itis_tsn="24769"/>
  <item-creation item="varieties#prunus_avium_brune_de_romeries" parent="prunus_armeniaca" itis_tsn="24769"/>
  <item-creation item="varieties#prunus_avium_cerise_blanc_nez" parent="prunus_armeniaca" itis_tsn="24769"/>
  <item-creation item="varieties#prunus_avium_cerise_blanche_de_wavrans_sur_l_aa" parent="prunus_armeniaca" itis_tsn="24769"/>
  <item-creation item="varieties#prunus_avium_cerise_blanche_d_harsigny" parent="prunus_armeniaca" itis_tsn="24769"/>
  <item-creation item="varieties#prunus_avium_cerise_de_moncheaux" parent="prunus_armeniaca" itis_tsn="24769"/>
  <item-creation item="varieties#prunus_avium_cerise_d_enguinegatte" parent="prunus_armeniaca" itis_tsn="24769"/>
  <item-creation item="varieties#prunus_avium_cerise_du_quesnoy" parent="prunus_armeniaca" itis_tsn="24769"/>
  <item-creation item="varieties#prunus_avium_cerise_du_sars" parent="prunus_armeniaca" itis_tsn="24769"/>
  <item-creation item="varieties#prunus_avium_cerise_peloa" parent="prunus_armeniaca" itis_tsn="24769"/>
  <item-creation item="varieties#prunus_avium_xapata_chapata" parent="prunus_armeniaca" itis_tsn="24769"/>
  <item-creation item="varieties#prunus_avium_coeur_de_pigeon_noir" parent="prunus_armeniaca" itis_tsn="24769"/>
  <item-creation item="varieties#prunus_avium_gascogne_tardive_de_seninghem" parent="prunus_armeniaca" itis_tsn="24769"/>
  <item-creation item="varieties#prunus_avium_gros_bigarreau_de_la_groise" parent="prunus_armeniaca" itis_tsn="24769"/>
  <item-creation item="varieties#prunus_avium_gros_bigarreau_d_eperlecques" parent="prunus_armeniaca" itis_tsn="24769"/>
  <item-creation item="varieties#prunus_avium_grosse_cerise_blanche_de_verchocq" parent="prunus_armeniaca" itis_tsn="24769"/>
  <item-creation item="varieties#prunus_avium_grosse_cerise_tardive" parent="prunus_armeniaca" itis_tsn="24769"/>
  <item-creation item="varieties#prunus_avium_guigne_noire_de_ruesnes" parent="prunus_armeniaca" itis_tsn="24769"/>
  <item-creation item="varieties#prunus_avium_guigne_noire_du_pevele" parent="prunus_armeniaca" itis_tsn="24769"/>
  <item-creation item="varieties#prunus_avium_guindoux_du_poitou" parent="prunus_armeniaca" itis_tsn="24769"/>
  <item-creation item="varieties#prunus_avium_marin" parent="prunus_armeniaca" itis_tsn="24769"/>
  <item-creation item="varieties#prunus_avium_merisier" parent="prunus_armeniaca" itis_tsn="24769"/>
  <item-creation item="varieties#prunus_avium_mourette_amourette" parent="prunus_armeniaca" itis_tsn="24769"/>
  <item-creation item="varieties#prunus_avium_muant" parent="prunus_armeniaca" itis_tsn="24769"/>
  <item-creation item="varieties#prunus_avium_noire_d_itxassou_geresi_belxa" parent="prunus_armeniaca" itis_tsn="24769"/>
  <item-creation item="varieties#prunus_avium_petite_noire" parent="prunus_armeniaca" itis_tsn="24769"/>
  <item-creation item="varieties#prunus_avium_precoce_de_la_marche" parent="prunus_armeniaca" itis_tsn="24769"/>
  <item-creation item="varieties#prunus_avium_precoce_du_pays" parent="prunus_armeniaca" itis_tsn="24769"/>
  <item-creation item="varieties#prunus_avium_triaux_des_fondettes" parent="prunus_armeniaca" itis_tsn="24769"/>
  <item-creation item="varieties#prunus_cerasus_griotte_de_leme" parent="prunus_cerasus" itis_tsn="24773"/>
  <item-creation item="varieties#prunus_cerasus_griotte_du_vieux_conde" parent="prunus_cerasus" itis_tsn="24773"/>
  <item-creation item="varieties#prunus_cerasus_griotte_jaune_d_oullins" parent="prunus_cerasus" itis_tsn="24773"/>
  <item-creation item="varieties#prunus_cerasus_griotte_precoce_de_samer" parent="prunus_cerasus" itis_tsn="24773"/>
  <item-creation item="varieties#prunus_persica_roussane_de_monein" parent="prunus_persica" itis_tsn="24765"/>
  <item-creation item="varieties#pyrus_communis_beurre_d_anjou" parent="pyrus_communis" itis_tsn="25295"/>
  <item-creation item="varieties#pyrus_communis_beurre_de_l_assomption" parent="pyrus_communis" itis_tsn="25295"/>
  <item-creation item="varieties#pyrus_communis_beurre_lebrun" parent="prunus_persica" itis_tsn="24765"/>
  <item-creation item="varieties#pyrus_communis_beurre_surperfin" parent="prunus_persica" itis_tsn="24765"/>
  <item-creation item="varieties#pyrus_communis_bonnissime_de_la_sarthe" parent="prunus_persica" itis_tsn="24765"/>
  <item-creation item="varieties#pyrus_communis_comtesse_de_paris" parent="prunus_persica" itis_tsn="24765"/>
  <item-creation item="varieties#pyrus_communis_comelie" parent="prunus_persica" itis_tsn="24765"/>
  <item-creation item="varieties#pyrus_communis_cuisse_dame" parent="prunus_persica" itis_tsn="24765"/>
  <item-creation item="varieties#pyrus_communis_cure" parent="prunus_persica" itis_tsn="24765"/>
  <item-creation item="varieties#pyrus_communis_dayenne" parent="prunus_persica" itis_tsn="24765"/>
  <item-creation item="varieties#pyrus_communis_duchesse_de_poitiers" parent="prunus_persica" itis_tsn="24765"/>
  <item-creation item="varieties#pyrus_communis_duchesse_du_berry" parent="prunus_persica" itis_tsn="24765"/>
  <item-creation item="varieties#pyrus_communis_eugene_thirriot" parent="prunus_persica" itis_tsn="24765"/>
  <item-creation item="varieties#pyrus_communis_fondante_thirriot" parent="prunus_persica" itis_tsn="24765"/>
  <item-creation item="varieties#pyrus_communis_grosse_louise" parent="prunus_persica" itis_tsn="24765"/>
  <item-creation item="varieties#pyrus_communis_jean_nicolas" parent="prunus_persica" itis_tsn="24765"/>
  <item-creation item="varieties#pyrus_communis_legipont" parent="prunus_persica" itis_tsn="24765"/>
  <item-creation item="varieties#pyrus_communis_madame_gregoire" parent="prunus_persica" itis_tsn="24765"/>
  <item-creation item="varieties#pyrus_communis_marguerite_marillat" parent="prunus_persica" itis_tsn="24765"/>
  <item-creation item="varieties#pyrus_communis_nipe_nime" parent="prunus_persica" itis_tsn="24765"/>
  <item-creation item="varieties#pyrus_communis_plovinne" parent="prunus_persica" itis_tsn="24765"/>
  <item-creation item="varieties#pyrus_communis_poire_a_clement" parent="prunus_persica" itis_tsn="24765"/>
  <item-creation item="varieties#pyrus_communis_poire_a_cote_d_or" parent="prunus_persica" itis_tsn="24765"/>
  <item-creation item="varieties#pyrus_communis_poire_a_cuire_grise_de_wierre_au_bois" parent="prunus_persica" itis_tsn="24765"/>
  <item-creation item="varieties#pyrus_communis_poire_blanquette" parent="prunus_persica" itis_tsn="24765"/>
  <item-creation item="varieties#pyrus_communis_poire_boutoc_poire_d_ange" parent="prunus_persica" itis_tsn="24765"/>
  <item-creation item="varieties#pyrus_communis_poire_caillaou_rosat" parent="prunus_persica" itis_tsn="24765"/>
  <item-creation item="varieties#pyrus_communis_poire_catillac" parent="prunus_persica" itis_tsn="24765"/>
  <item-creation item="varieties#pyrus_communis_poire_citron" parent="prunus_persica" itis_tsn="24765"/>
  <item-creation item="varieties#pyrus_communis_poire_cure" parent="prunus_persica" itis_tsn="24765"/>
  <item-creation item="varieties#pyrus_communis_poire_d_anis" parent="prunus_persica" itis_tsn="24765"/>
  <item-creation item="varieties#pyrus_communis_poire_d_aout_de_seninghem" parent="prunus_persica" itis_tsn="24765"/>
  <item-creation item="varieties#pyrus_communis_poire_de_beton" parent="prunus_persica" itis_tsn="24765"/>
  <item-creation item="varieties#pyrus_communis_poire_de_beurre" parent="prunus_persica" itis_tsn="24765"/>
  <item-creation item="varieties#pyrus_communis_poire_de_blanc" parent="prunus_persica" itis_tsn="24765"/>
  <item-creation item="varieties#pyrus_communis_poire_de_calot" parent="prunus_persica" itis_tsn="24765"/>
  <item-creation item="varieties#pyrus_communis_poire_de_cave" parent="prunus_persica" itis_tsn="24765"/>
  <item-creation item="varieties#pyrus_communis_poire_de_cheminee" parent="prunus_persica" itis_tsn="24765"/>
  <item-creation item="varieties#pyrus_communis_poire_de_cure" parent="prunus_persica" itis_tsn="24765"/>
  <item-creation item="varieties#pyrus_communis_poire_de_fret" parent="prunus_persica" itis_tsn="24765"/>
  <item-creation item="varieties#pyrus_communis_poire_de_guinette" parent="prunus_persica" itis_tsn="24765"/>
  <item-creation item="varieties#pyrus_communis_poire_de_jargonelle" parent="prunus_persica" itis_tsn="24765"/>
  <item-creation item="varieties#pyrus_communis_poire_de_livre" parent="prunus_persica" itis_tsn="24765"/>
  <item-creation item="varieties#pyrus_communis_poire_de_loup" parent="prunus_persica" itis_tsn="24765"/>
  <item-creation item="varieties#pyrus_communis_poire_de_marsanneix" parent="prunus_persica" itis_tsn="24765"/>
  <item-creation item="varieties#pyrus_communis_poire_de_moreau" parent="prunus_persica" itis_tsn="24765"/>
  <item-creation item="varieties#pyrus_communis_poire_de_petit_roux" parent="prunus_persica" itis_tsn="24765"/>
  <item-creation item="varieties#pyrus_communis_poire_de_rapace" parent="prunus_persica" itis_tsn="24765"/>
  <item-creation item="varieties#pyrus_communis_poire_de_rateau_rouge" parent="prunus_persica" itis_tsn="24765"/>
  <item-creation item="varieties#pyrus_communis_poire_de_roulee" parent="prunus_persica" itis_tsn="24765"/>
  <item-creation item="varieties#pyrus_communis_poire_de_saint_antoine" parent="prunus_persica" itis_tsn="24765"/>
  <item-creation item="varieties#pyrus_communis_poire_de_sang" parent="prunus_persica" itis_tsn="24765"/>
  <item-creation item="varieties#pyrus_communis_poire_de_vierge" parent="prunus_persica" itis_tsn="24765"/>
  <item-creation item="varieties#pyrus_communis_poire_duchesse_d_angouleme" parent="prunus_persica" itis_tsn="24765"/>
  <item-creation item="varieties#pyrus_communis_poire_epargne_cuisse_madame" parent="prunus_persica" itis_tsn="24765"/>
  <item-creation item="varieties#pyrus_communis_poire_marguerite_marillat" parent="prunus_persica" itis_tsn="24765"/>
  <item-creation item="varieties#pyrus_communis_poire_monsallard_epine_d_ete" parent="prunus_persica" itis_tsn="24765"/>
  <item-creation item="varieties#pyrus_communis_poire_mouille_bouche_jansemine" parent="prunus_persica" itis_tsn="24765"/>
  <item-creation item="varieties#pyrus_communis_poire_notre_dame" parent="prunus_persica" itis_tsn="24765"/>
  <item-creation item="varieties#pyrus_communis_poire_orange" parent="prunus_persica" itis_tsn="24765"/>
  <item-creation item="varieties#pyrus_communis_poire_perou_d_argent" parent="prunus_persica" itis_tsn="24765"/>
  <item-creation item="varieties#pyrus_communis_poire_reinette" parent="prunus_persica" itis_tsn="24765"/>
  <item-creation item="varieties#pyrus_communis_poire_saint_jean" parent="prunus_persica" itis_tsn="24765"/>
  <item-creation item="varieties#pyrus_communis_poire_sucre_vert" parent="prunus_persica" itis_tsn="24765"/>
  <item-creation item="varieties#pyrus_communis_poire_de_mare" parent="prunus_persica" itis_tsn="24765"/>
  <item-creation item="varieties#pyrus_communis_rivailles" parent="prunus_persica" itis_tsn="24765"/>
  <item-creation item="varieties#pyrus_communis_saint_mathieu" parent="prunus_persica" itis_tsn="24765"/>
  <item-creation item="varieties#pyrus_communis_sans_pepins" parent="prunus_persica" itis_tsn="24765"/>
  <item-creation item="varieties#pyrus_communis_sucree_vert_de_montlucon" parent="prunus_persica" itis_tsn="24765"/>
  <item-creation item="varieties#pyrus_communis_sucree_de_montlucon" parent="prunus_persica" itis_tsn="24765"/>
  <item-creation item="varieties#pyrus_communis_triomphe_de_vienne" parent="prunus_persica" itis_tsn="24765"/>
  <item-creation item="varieties#malus_pumila" parent="malus" itis_tsn="25254"/>
  <item-creation item="varieties#malus_pumila_a_cotes" parent="malus_pumila" itis_tsn="25262"/>
  <item-creation item="varieties#malus_pumila_amere_nouvelle" parent="malus_pumila" itis_tsn="25262"/>
  <item-creation item="varieties#malus_pumila_api_d_ete" parent="malus_pumila" itis_tsn="25262"/>
  <item-creation item="varieties#malus_pumila_api_d_orange" parent="malus_pumila" itis_tsn="25262"/>
  <item-creation item="varieties#malus_pumila_api_double_rose_ou_api_rouge" parent="malus_pumila" itis_tsn="25262"/>
  <item-creation item="varieties#malus_pumila_api_etoile" parent="malus_pumila" itis_tsn="25262"/>
  <item-creation item="varieties#malus_pumila_argiliere_ou_dimoutiere" parent="malus_pumila" itis_tsn="25262"/>
  <item-creation item="varieties#malus_pumila_armagnac" parent="malus_pumila" itis_tsn="25262"/>
  <item-creation item="varieties#malus_pumila_ascahire" parent="malus_pumila" itis_tsn="25262"/>
  <item-creation item="varieties#malus_pumila_azeroli_anise_mazoreli" parent="malus_pumila" itis_tsn="25262"/>
  <item-creation item="varieties#malus_pumila_baguette_d_hiver" parent="malus_pumila" itis_tsn="25262"/>
  <item-creation item="varieties#malus_pumila_baguette_violette" parent="malus_pumila" itis_tsn="25262"/>
  <item-creation item="varieties#malus_pumila_bailly_ou_belle_fleur_de_st_benoit" parent="malus_pumila" itis_tsn="25262"/>
  <item-creation item="varieties#malus_pumila_barbarie" parent="malus_pumila" itis_tsn="25262"/>
  <item-creation item="varieties#malus_pumila_beaurichard" parent="malus_pumila" itis_tsn="25262"/>
  <item-creation item="varieties#malus_pumila_bec_d_oie_du_cher" parent="malus_pumila" itis_tsn="25262"/>
  <item-creation item="varieties#malus_pumila_belle_de_juillet" parent="malus_pumila" itis_tsn="25262"/>
  <item-creation item="varieties#malus_pumila_belle_de_linards" parent="malus_pumila" itis_tsn="25262"/>
  <item-creation item="varieties#malus_pumila_belle_de_pontoise" parent="malus_pumila" itis_tsn="25262"/>
  <item-creation item="varieties#malus_pumila_belle_du_bois" parent="malus_pumila" itis_tsn="25262"/>
  <item-creation item="varieties#malus_pumila_belle_fille_de_la_creuse" parent="malus_pumila" itis_tsn="25262"/>
  <item-creation item="varieties#malus_pumila_belle_fleur_double" parent="malus_pumila" itis_tsn="25262"/>
  <item-creation item="varieties#malus_pumila_belle_fleur_simple_petit_bon_ente" parent="malus_pumila" itis_tsn="25262"/>
  <item-creation item="varieties#malus_pumila_belle_louronnaise_nez_de_veau" parent="malus_pumila" itis_tsn="25262"/>
  <item-creation item="varieties#malus_pumila_belle_fille_de_l_indre" parent="malus_pumila" itis_tsn="25262"/>
  <item-creation item="varieties#malus_pumila_belle-fille_de_la_creuse" parent="malus_pumila" itis_tsn="25262"/>
  <item-creation item="varieties#malus_pumila_beurriere" parent="malus_pumila" itis_tsn="25262"/>
  <item-creation item="varieties#malus_pumila_blanc_d_espagne" parent="malus_pumila" itis_tsn="25262"/>
  <item-creation item="varieties#malus_pumila_bon_ente_belge" parent="malus_pumila" itis_tsn="25262"/>
  <item-creation item="varieties#malus_pumila_bon_ente_charbonnier" parent="malus_pumila" itis_tsn="25262"/>
  <item-creation item="varieties#malus_pumila_bondon" parent="malus_pumila" itis_tsn="25262"/>
  <item-creation item="varieties#malus_pumila_bonnet_carre" parent="malus_pumila" itis_tsn="25262"/>
  <item-creation item="varieties#malus_pumila_boulonnex" parent="malus_pumila" itis_tsn="25262"/>
  <item-creation item="varieties#malus_pumila_bouviere" parent="malus_pumila" itis_tsn="25262"/>
  <item-creation item="varieties#malus_pumila_cabarette" parent="malus_pumila" itis_tsn="25262"/>
  <item-creation item="varieties#malus_pumila_calvi_blanc" parent="malus_pumila" itis_tsn="25262"/>
  <item-creation item="varieties#malus_pumila_calville_rouge_caramille" parent="malus_pumila" itis_tsn="25262"/>
  <item-creation item="varieties#malus_pumila_calvin" parent="malus_pumila" itis_tsn="25262"/>
  <item-creation item="varieties#malus_pumila_carisi_a_longue_queue" parent="malus_pumila" itis_tsn="25262"/>
  <item-creation item="varieties#malus_pumila_cassou_de_casse" parent="malus_pumila" itis_tsn="25262"/>
  <item-creation item="varieties#malus_pumila_cellini" parent="malus_pumila" itis_tsn="25262"/>
  <item-creation item="varieties#malus_pumila_chailleux" parent="malus_pumila" itis_tsn="25262"/>
  <item-creation item="varieties#malus_pumila_chataignier" parent="malus_pumila" itis_tsn="25262"/>
  <item-creation item="varieties#malus_pumila_chaux" parent="malus_pumila" itis_tsn="25262"/>
  <item-creation item="varieties#malus_pumila_choureau_reinette_choureau" parent="malus_pumila" itis_tsn="25262"/>
  <item-creation item="varieties#malus_pumila_clairefontaine" parent="malus_pumila" itis_tsn="25262"/>
  <item-creation item="varieties#malus_pumila_coing" parent="malus_pumila" itis_tsn="25262"/>
  <item-creation item="varieties#malus_pumila_colapuis" parent="malus_pumila" itis_tsn="25262"/>
  <item-creation item="varieties#malus_pumila_coquette_d_auvergne" parent="malus_pumila" itis_tsn="25262"/>
  <item-creation item="varieties#malus_pumila_court_pendu_d_espagne" parent="malus_pumila" itis_tsn="25262"/>
  <item-creation item="varieties#malus_pumila_court_pendu_gris_du_limousin" parent="malus_pumila" itis_tsn="25262"/>
  <item-creation item="varieties#malus_pumila_court_pendu_rouge" parent="malus_pumila" itis_tsn="25262"/>
  <item-creation item="varieties#malus_pumila_court_pendu_rouge_du_lot_et_garonne" parent="malus_pumila" itis_tsn="25262"/>
  <item-creation item="varieties#malus_pumila_court_pendu_gris" parent="malus_pumila" itis_tsn="25262"/>
  <item-creation item="varieties#malus_pumila_coutras" parent="malus_pumila" itis_tsn="25262"/>
  <item-creation item="varieties#malus_pumila_coxs_rouge_des_flandres" parent="malus_pumila" itis_tsn="25262"/>
  <item-creation item="varieties#malus_pumila_crarouge" parent="malus_pumila" itis_tsn="25262"/>
  <item-creation item="varieties#malus_pumila_cravert" parent="malus_pumila" itis_tsn="25262"/>
  <item-creation item="varieties#malus_pumila_espagne" parent="malus_pumila" itis_tsn="25262"/>
  <item-creation item="varieties#malus_pumila_de_bonde" parent="malus_pumila" itis_tsn="25262"/>
  <item-creation item="varieties#malus_pumila_de_jeu" parent="malus_pumila" itis_tsn="25262"/>
  <item-creation item="varieties#malus_pumila_de_estre_ou_sainte_germaine" parent="malus_pumila" itis_tsn="25262"/>
  <item-creation item="varieties#malus_pumila_de_tendre" parent="malus_pumila" itis_tsn="25262"/>
  <item-creation item="varieties#malus_pumila_demie_double" parent="malus_pumila" itis_tsn="25262"/>
  <item-creation item="varieties#malus_pumila_double_a_l_huile" parent="malus_pumila" itis_tsn="25262"/>
  <item-creation item="varieties#malus_pumila_double_belle_fleur" parent="malus_pumila" itis_tsn="25262"/>
  <item-creation item="varieties#malus_pumila_double_bon_pommier" parent="malus_pumila" itis_tsn="25262"/>
  <item-creation item="varieties#malus_pumila_double_bon_pommier_rouge" parent="malus_pumila" itis_tsn="25262"/>
  <item-creation item="varieties#malus_pumila_doux_corier" parent="malus_pumila" itis_tsn="25262"/>
  <item-creation item="varieties#malus_pumila_douzandin" parent="malus_pumila" itis_tsn="25262"/>
  <item-creation item="varieties#malus_pumila_drap_d_or_de_la_creuse" parent="malus_pumila" itis_tsn="25262"/>
  <item-creation item="varieties#malus_pumila_du_verger" parent="malus_pumila" itis_tsn="25262"/>
  <item-creation item="varieties#malus_pumila_eri_sagarra" parent="malus_pumila" itis_tsn="25262"/>
  <item-creation item="varieties#malus_pumila_fer_du_cher" parent="malus_pumila" itis_tsn="25262"/>
  <item-creation item="varieties#malus_pumila_feuillot" parent="malus_pumila" itis_tsn="25262"/>
  <item-creation item="varieties#malus_pumila_feuilloux" parent="malus_pumila" itis_tsn="25262"/>
  <item-creation item="varieties#malus_pumila_finette_de_gallardon" parent="malus_pumila" itis_tsn="25262"/>
  <item-creation item="varieties#malus_pumila_fouillaud" parent="malus_pumila" itis_tsn="25262"/>
  <item-creation item="varieties#malus_pumila_franc_rougeau" parent="malus_pumila" itis_tsn="25262"/>
  <item-creation item="varieties#malus_pumila_gaillarde" parent="malus_pumila" itis_tsn="25262"/>
  <item-creation item="varieties#malus_pumila_germaine" parent="malus_pumila" itis_tsn="25262"/>
  <item-creation item="varieties#malus_pumila_gold_reinette" parent="malus_pumila" itis_tsn="25262"/>
  <item-creation item="varieties#malus_pumila_gosselet" parent="malus_pumila" itis_tsn="25262"/>
  <item-creation item="varieties#malus_pumila_gris_baudet" parent="malus_pumila" itis_tsn="25262"/>
  <item-creation item="varieties#malus_pumila_gris_brabant" parent="malus_pumila" itis_tsn="25262"/>
  <item-creation item="varieties#malus_pumila_gros_locard" parent="malus_pumila" itis_tsn="25262"/>
  <item-creation item="varieties#malus_pumila_gros_museau_de_lievre_blanc" parent="malus_pumila" itis_tsn="25262"/>
  <item-creation item="varieties#malus_pumila_gueule_de_mouton" parent="malus_pumila" itis_tsn="25262"/>
  <item-creation item="varieties#malus_pumila_hollande_rouge" parent="malus_pumila" itis_tsn="25262"/>
  <item-creation item="varieties#malus_pumila_hybride_golden_x_cassou_106" parent="malus_pumila" itis_tsn="25262"/>
  <item-creation item="varieties#malus_pumila_hybride_golden_x_cassou_43" parent="malus_pumila" itis_tsn="25262"/>
  <item-creation item="varieties#malus_pumila_hybride_golden_x_cassou_89" parent="malus_pumila" itis_tsn="25262"/>
  <item-creation item="varieties#malus_pumila_jacques_lebel" parent="malus_pumila" itis_tsn="25262"/>
  <item-creation item="varieties#malus_pumila_jincoa_sagarra_pomme_dieu" parent="malus_pumila" itis_tsn="25262"/>
  <item-creation item="varieties#malus_pumila_la_douce" parent="malus_pumila" itis_tsn="25262"/>
  <item-creation item="varieties#malus_pumila_lanscailler" parent="malus_pumila" itis_tsn="25262"/>
  <item-creation item="varieties#malus_pumila_longue_queue" parent="malus_pumila" itis_tsn="25262"/>
  <item-creation item="varieties#malus_pumila_luche" parent="malus_pumila" itis_tsn="25262"/>
  <item-creation item="varieties#malus_pumila_marie_doudou" parent="malus_pumila" itis_tsn="25262"/>
  <item-creation item="varieties#malus_pumila_marseigna" parent="malus_pumila" itis_tsn="25262"/>
  <item-creation item="varieties#malus_pumila_michotte_de_gallardon" parent="malus_pumila" itis_tsn="25262"/>
  <item-creation item="varieties#malus_pumila_museau_de_lievre_jaune" parent="malus_pumila" itis_tsn="25262"/>
  <item-creation item="varieties#malus_pumila_museau_de_lievre_rouge_du_bearn" parent="malus_pumila" itis_tsn="25262"/>
  <item-creation item="varieties#malus_pumila_normandie_blanc" parent="malus_pumila" itis_tsn="25262"/>
  <item-creation item="varieties#malus_pumila_ontario" parent="malus_pumila" itis_tsn="25262"/>
  <item-creation item="varieties#malus_pumila_pay_bou_andre_maria_sagarra" parent="malus_pumila" itis_tsn="25262"/>
  <item-creation item="varieties#malus_pumila_perasse_de_ganpeaxaperasse_de_nay" parent="malus_pumila" itis_tsn="25262"/>
  <item-creation item="varieties#malus_pumila_perregue" parent="malus_pumila" itis_tsn="25262"/>
  <item-creation item="varieties#malus_pumila_petit_museau_de_lievre_blanc" parent="malus_pumila" itis_tsn="25262"/>
  <item-creation item="varieties#malus_pumila_petite_madeleine" parent="malus_pumila" itis_tsn="25262"/>
  <item-creation item="varieties#malus_pumila_pigeonnette" parent="malus_pumila" itis_tsn="25262"/>
  <item-creation item="varieties#malus_pumila_pineau" parent="malus_pumila" itis_tsn="25262"/>
  <item-creation item="varieties#malus_pumila_pomme_cloche" parent="malus_pumila" itis_tsn="25262"/>
  <item-creation item="varieties#malus_pumila_pomme_d_albret" parent="malus_pumila" itis_tsn="25262"/>
  <item-creation item="varieties#malus_pumila_pomme_d_anis_rosalie" parent="malus_pumila" itis_tsn="25262"/>
  <item-creation item="varieties#malus_pumila_pomme_d_anis_tardive" parent="malus_pumila" itis_tsn="25262"/>
  <item-creation item="varieties#malus_pumila_pomme_d_arengosse" parent="malus_pumila" itis_tsn="25262"/>
  <item-creation item="varieties#malus_pumila_pomme_d_argent" parent="malus_pumila" itis_tsn="25262"/>
  <item-creation item="varieties#malus_pumila_pomme_d_enfer_bordes" parent="malus_pumila" itis_tsn="25262"/>
  <item-creation item="varieties#malus_pumila_pomme_d_ile" parent="malus_pumila" itis_tsn="25262"/>
  <item-creation item="varieties#malus_pumila_pomme_de_bedeau" parent="malus_pumila" itis_tsn="25262"/>
  <item-creation item="varieties#malus_pumila_pomme_de_behier" parent="malus_pumila" itis_tsn="25262"/>
  <item-creation item="varieties#malus_pumila_pomme_de_beurre" parent="malus_pumila" itis_tsn="25262"/>
  <item-creation item="varieties#malus_pumila_pomme_de_bouet" parent="malus_pumila" itis_tsn="25262"/>
  <item-creation item="varieties#malus_pumila_pomme_de_choconin" parent="malus_pumila" itis_tsn="25262"/>
  <item-creation item="varieties#malus_pumila_pomme_de_coudre" parent="malus_pumila" itis_tsn="25262"/>
  <item-creation item="varieties#malus_pumila_pomme_de_douce_dame_franchon" parent="malus_pumila" itis_tsn="25262"/>
  <item-creation item="varieties#malus_pumila_pomme_de_fer" parent="malus_pumila" itis_tsn="25262"/>
  <item-creation item="varieties#malus_pumila_pomme_de_la_saint_jean" parent="malus_pumila" itis_tsn="25262"/>
  <item-creation item="varieties#malus_pumila_pomme_de_loumarin" parent="malus_pumila" itis_tsn="25262"/>
  <item-creation item="varieties#malus_pumila_pomme_de_madeleine" parent="malus_pumila" itis_tsn="25262"/>
  <item-creation item="varieties#malus_pumila_pomme_de_maillard" parent="malus_pumila" itis_tsn="25262"/>
  <item-creation item="varieties#malus_pumila_pomme_de_moisson" parent="malus_pumila" itis_tsn="25262"/>
  <item-creation item="varieties#malus_pumila_pomme_de_passe" parent="malus_pumila" itis_tsn="25262"/>
  <item-creation item="varieties#malus_pumila_pomme_de_pecantin" parent="malus_pumila" itis_tsn="25262"/>
  <item-creation item="varieties#malus_pumila_pomme_de_puits" parent="malus_pumila" itis_tsn="25262"/>
  <item-creation item="varieties#malus_pumila_pomme_de_rose" parent="malus_pumila" itis_tsn="25262"/>
  <item-creation item="varieties#malus_pumila_pomme_de_rougette" parent="malus_pumila" itis_tsn="25262"/>
  <item-creation item="varieties#malus_pumila_pomme_de_saint_michel" parent="malus_pumila" itis_tsn="25262"/>
  <item-creation item="varieties#malus_pumila_pomme_de_sore" parent="malus_pumila" itis_tsn="25262"/>
  <item-creation item="varieties#malus_pumila_pomme_de_tendron" parent="malus_pumila" itis_tsn="25262"/>
  <item-creation item="varieties#malus_pumila_pomme_dieu" parent="malus_pumila" itis_tsn="25262"/>
  <item-creation item="varieties#malus_pumila_pomme_glace" parent="malus_pumila" itis_tsn="25262"/>
  <item-creation item="varieties#malus_pumila_pomme_jacquet" parent="malus_pumila" itis_tsn="25262"/>
  <item-creation item="varieties#malus_pumila_pomme_jean_de_grignon" parent="malus_pumila" itis_tsn="25262"/>
  <item-creation item="varieties#malus_pumila_pomme_orange" parent="malus_pumila" itis_tsn="25262"/>
  <item-creation item="varieties#malus_pumila_pomme_poire" parent="malus_pumila" itis_tsn="25262"/>
  <item-creation item="varieties#malus_pumila_pomme_taupe" parent="malus_pumila" itis_tsn="25262"/>
  <item-creation item="varieties#malus_pumila_pouzac" parent="malus_pumila" itis_tsn="25262"/>
  <item-creation item="varieties#malus_pumila_pouzaraque" parent="malus_pumila" itis_tsn="25262"/>
  <item-creation item="varieties#malus_pumila_precoce_de_wirwignes" parent="malus_pumila" itis_tsn="25262"/>
  <item-creation item="varieties#malus_pumila_quarantaine_d_hiver" parent="malus_pumila" itis_tsn="25262"/>
  <item-creation item="varieties#malus_pumila_rador" parent="malus_pumila" itis_tsn="25262"/>
  <item-creation item="varieties#malus_pumila_rambour_d_hiver" parent="malus_pumila" itis_tsn="25262"/>
  <item-creation item="varieties#malus_pumila_razot" parent="malus_pumila" itis_tsn="25262"/>
  <item-creation item="varieties#malus_pumila_reale_d_entraygue" parent="malus_pumila" itis_tsn="25262"/>
  <item-creation item="varieties#malus_pumila_redondelle_blandureau" parent="malus_pumila" itis_tsn="25262"/>
  <item-creation item="varieties#malus_pumila_reinette_baumann" parent="malus_pumila" itis_tsn="25262"/>
  <item-creation item="varieties#malus_pumila_reinette_bure" parent="malus_pumila" itis_tsn="25262"/>
  <item-creation item="varieties#malus_pumila_reinette_clochard" parent="malus_pumila" itis_tsn="25262"/>
  <item-creation item="varieties#malus_pumila_reinette_d_angleterre" parent="malus_pumila" itis_tsn="25262"/>
  <item-creation item="varieties#malus_pumila_reinette_de_brive_de_l_estre" parent="malus_pumila" itis_tsn="25262"/>
  <item-creation item="varieties#malus_pumila_reinette_de_correze" parent="malus_pumila" itis_tsn="25262"/>
  <item-creation item="varieties#malus_pumila_reinette_de_flandre" parent="malus_pumila" itis_tsn="25262"/>
  <item-creation item="varieties#malus_pumila_reinette_de_france" parent="malus_pumila" itis_tsn="25262"/>
  <item-creation item="varieties#malus_pumila_reinette_de_fugelan" parent="malus_pumila" itis_tsn="25262"/>
  <item-creation item="varieties#malus_pumila_reinette_de_hollande" parent="malus_pumila" itis_tsn="25262"/>
  <item-creation item="varieties#malus_pumila_reinette_de_saintonge" parent="malus_pumila" itis_tsn="25262"/>
  <item-creation item="varieties#malus_pumila_reinette_de_villerette" parent="malus_pumila" itis_tsn="25262"/>
  <item-creation item="varieties#malus_pumila_reinette_de_waleffe" parent="malus_pumila" itis_tsn="25262"/>
  <item-creation item="varieties#malus_pumila_reinette_des_capucins" parent="malus_pumila" itis_tsn="25262"/>
  <item-creation item="varieties#malus_pumila_reinette_des_chatres" parent="malus_pumila" itis_tsn="25262"/>
  <item-creation item="varieties#malus_pumila_reinette_descardre" parent="malus_pumila" itis_tsn="25262"/>
  <item-creation item="varieties#malus_pumila_reinette_doree_reinette_d_or" parent="malus_pumila" itis_tsn="25262"/>
  <item-creation item="varieties#malus_pumila_reinette_doree_de_l_indre" parent="malus_pumila" itis_tsn="25262"/>
  <item-creation item="varieties#malus_pumila_reinette_du_mans" parent="malus_pumila" itis_tsn="25262"/>
  <item-creation item="varieties#malus_pumila_reinette_etoilee" parent="malus_pumila" itis_tsn="25262"/>
  <item-creation item="varieties#malus_pumila_reinette_grise_avancee" parent="malus_pumila" itis_tsn="25262"/>
  <item-creation item="varieties#malus_pumila_reinette_hernaut" parent="malus_pumila" itis_tsn="25262"/>
  <item-creation item="varieties#malus_pumila_reinette_jaune" parent="malus_pumila" itis_tsn="25262"/>
  <item-creation item="varieties#malus_pumila_reinette_marbree_d_auvergne" parent="malus_pumila" itis_tsn="25262"/>
  <item-creation item="varieties#malus_pumila_reinette_marbree_de_la_creuse" parent="malus_pumila" itis_tsn="25262"/>
  <item-creation item="varieties#malus_pumila_reinette_rouge_de_la_creuse" parent="malus_pumila" itis_tsn="25262"/>
  <item-creation item="varieties#malus_pumila_reinette_sans_pepin" parent="malus_pumila" itis_tsn="25262"/>
  <item-creation item="varieties#malus_pumila_reinette_tardive_d_englefontaine_la_clermontoise" parent="malus_pumila" itis_tsn="25262"/>
  <item-creation item="varieties#malus_pumila_rene_vert_reina_verte" parent="malus_pumila" itis_tsn="25262"/>
  <item-creation item="varieties#malus_pumila_roquet_rouge" parent="malus_pumila" itis_tsn="25262"/>
  <item-creation item="varieties#malus_pumila_rose_de_benauge" parent="malus_pumila" itis_tsn="25262"/>
  <item-creation item="varieties#malus_pumila_rose_de_hollande" parent="malus_pumila" itis_tsn="25262"/>
  <item-creation item="varieties#malus_pumila_rose_de_saint_yrieix" parent="malus_pumila" itis_tsn="25262"/>
  <item-creation item="varieties#malus_pumila_rose_de_virginie_ou_rose_d_ete" parent="malus_pumila" itis_tsn="25262"/>
  <item-creation item="varieties#malus_pumila_rose_du_perche" parent="malus_pumila" itis_tsn="25262"/>
  <item-creation item="varieties#malus_pumila_rouge_d_automne" parent="malus_pumila" itis_tsn="25262"/>
  <item-creation item="varieties#malus_pumila_rouillaud" parent="malus_pumila" itis_tsn="25262"/>
  <item-creation item="varieties#malus_pumila_ruban_1" parent="malus_pumila" itis_tsn="25262"/>
  <item-creation item="varieties#malus_pumila_saint_jean_transparente_blanche" parent="malus_pumila" itis_tsn="25262"/>
  <item-creation item="varieties#malus_pumila_saint_brisson" parent="malus_pumila" itis_tsn="25262"/>
  <item-creation item="varieties#malus_pumila_saint_laurent_de_brenne" parent="malus_pumila" itis_tsn="25262"/>
  <item-creation item="varieties#malus_pumila_saint_michel_le_coudic" parent="malus_pumila" itis_tsn="25262"/>
  <item-creation item="varieties#malus_pumila_sang_de_boeuf" parent="malus_pumila" itis_tsn="25262"/>
  <item-creation item="varieties#malus_pumila_sans_graine" parent="malus_pumila" itis_tsn="25262"/>
  <item-creation item="varieties#malus_pumila_sans_pareille_de_peasgood" parent="malus_pumila" itis_tsn="25262"/>
  <item-creation item="varieties#malus_pumila_six_cotes" parent="malus_pumila" itis_tsn="25262"/>
  <item-creation item="varieties#malus_pumila_suzette" parent="malus_pumila" itis_tsn="25262"/>
  <item-creation item="varieties#malus_pumila_tardive_de_bouvignies_rambour_hiver" parent="malus_pumila" itis_tsn="25262"/>
  <item-creation item="varieties#malus_pumila_transparente_de_croncels" parent="malus_pumila" itis_tsn="25262"/>
  <item-creation item="varieties#malus_pumila_trelage" parent="malus_pumila" itis_tsn="25262"/>
  <item-creation item="varieties#malus_pumila_trompe_gelees" parent="malus_pumila" itis_tsn="25262"/>
  <item-creation item="varieties#malus_pumila_udarre_sagarra_apez_sagarra" parent="malus_pumila" itis_tsn="25262"/>
  <item-creation item="varieties#malus_pumila_vechter" parent="malus_pumila" itis_tsn="25262"/>
  <item-creation item="varieties#malus_pumila_vedette_du_bearn" parent="malus_pumila" itis_tsn="25262"/>
  <item-creation item="varieties#malus_pumila_verdale" parent="malus_pumila" itis_tsn="25262"/>
  <item-creation item="varieties#malus_pumila_verdin_d_automne" parent="malus_pumila" itis_tsn="25262"/>
  <item-creation item="varieties#malus_pumila_verdin_d_hiver" parent="malus_pumila" itis_tsn="25262"/>
  <item-creation item="varieties#malus_pumila_vermillon_d_espagne" parent="malus_pumila" itis_tsn="25262"/>
  <item-creation item="varieties#malus_pumila_vernade" parent="malus_pumila" itis_tsn="25262"/>
  <item-creation item="varieties#malus_pumila_vernajoux" parent="malus_pumila" itis_tsn="25262"/>
  <item-creation item="varieties#malus_pumila_vol_au_vent" parent="malus_pumila" itis_tsn="25262"/>
  <item-creation item="varieties#malus_pumila_alza_sagarra" parent="malus_pumila" itis_tsn="25262"/>
  <item-creation item="varieties#malus_pumila_ameres_de_bernieulles" parent="malus_pumila" itis_tsn="25262"/>
  <item-creation item="varieties#malus_pumila_anixa_antze_sagarra" parent="malus_pumila" itis_tsn="25262"/>
  <item-creation item="varieties#malus_pumila_azaou_sagarra" parent="malus_pumila" itis_tsn="25262"/>
  <item-creation item="varieties#malus_pumila_blanquette" parent="malus_pumila" itis_tsn="25262"/>
  <item-creation item="varieties#malus_pumila_bordelesa" parent="malus_pumila" itis_tsn="25262"/>
  <item-creation item="varieties#malus_pumila_bourdin_sagarra" parent="malus_pumila" itis_tsn="25262"/>
  <item-creation item="varieties#malus_pumila_cachao_sagarra" parent="malus_pumila" itis_tsn="25262"/>
  <item-creation item="varieties#malus_pumila_douzandin_cidre" parent="malus_pumila" itis_tsn="25262"/>
  <item-creation item="varieties#malus_pumila_entzea_sagarra" parent="malus_pumila" itis_tsn="25262"/>
  <item-creation item="varieties#malus_pumila_eri_sagarra_cidre" parent="malus_pumila" itis_tsn="25262"/>
  <item-creation item="varieties#malus_pumila_errezila_sagarra" parent="malus_pumila" itis_tsn="25262"/>
  <item-creation item="varieties#malus_pumila_estirochia_sagarra" parent="malus_pumila" itis_tsn="25262"/>
  <item-creation item="varieties#malus_pumila_eztica" parent="malus_pumila" itis_tsn="25262"/>
  <item-creation item="varieties#malus_pumila_gazi_loka" parent="malus_pumila" itis_tsn="25262"/>
  <item-creation item="varieties#malus_pumila_geza" parent="malus_pumila" itis_tsn="25262"/>
  <item-creation item="varieties#malus_pumila_geza_xurria" parent="malus_pumila" itis_tsn="25262"/>
  <item-creation item="varieties#malus_pumila_gordain_xurria" parent="malus_pumila" itis_tsn="25262"/>
  <item-creation item="varieties#malus_pumila_gorri" parent="malus_pumila" itis_tsn="25262"/>
  <item-creation item="varieties#malus_pumila_jinkoa_sagarra" parent="malus_pumila" itis_tsn="25262"/>
  <item-creation item="varieties#malus_pumila_koko_gorria" parent="malus_pumila" itis_tsn="25262"/>
  <item-creation item="varieties#malus_pumila_koko_xurria" parent="malus_pumila" itis_tsn="25262"/>
  <item-creation item="varieties#malus_pumila_kokua" parent="malus_pumila" itis_tsn="25262"/>
  <item-creation item="varieties#malus_pumila_libra_sagarra" parent="malus_pumila" itis_tsn="25262"/>
  <item-creation item="varieties#malus_pumila_mamula_xurri" parent="malus_pumila" itis_tsn="25262"/>
  <item-creation item="varieties#malus_pumila_marie_menard" parent="malus_pumila" itis_tsn="25262"/>
  <item-creation item="varieties#malus_pumila_panneterie" parent="malus_pumila" itis_tsn="25262"/>
  <item-creation item="varieties#malus_pumila_patzulua" parent="malus_pumila" itis_tsn="25262"/>
  <item-creation item="varieties#malus_pumila_peaxa" parent="malus_pumila" itis_tsn="25262"/>
  <item-creation item="varieties#malus_pumila_perasse_de_gan" parent="malus_pumila" itis_tsn="25262"/>
  <item-creation item="varieties#malus_pumila_perasse_de_nay" parent="malus_pumila" itis_tsn="25262"/>
  <item-creation item="varieties#malus_pumila_perasse_grise" parent="malus_pumila" itis_tsn="25262"/>
  <item-creation item="varieties#malus_pumila_perasse_jaune" parent="malus_pumila" itis_tsn="25262"/>
  <item-creation item="varieties#malus_pumila_roquet_rouge_cidre" parent="malus_pumila" itis_tsn="25262"/>
  <item-creation item="varieties#malus_pumila_rouge_extra_tres_tardive" parent="malus_pumila" itis_tsn="25262"/>
  <item-creation item="varieties#malus_pumila_urieta_sagarra" parent="malus_pumila" itis_tsn="25262"/>
  <item-creation item="varieties#malus_pumila_usta_xurria" parent="malus_pumila" itis_tsn="25262"/>
  <item-creation item="varieties#prunus_domestica_abricotee_jaune" parent="prunus_domestica" itis_tsn="24774"/>
  <item-creation item="varieties#prunus_domestica_amarblanc_amarouge" parent="prunus_domestica" itis_tsn="24774"/>
  <item-creation item="varieties#prunus_domestica_balosse" parent="prunus_domestica" itis_tsn="24774"/>
  <item-creation item="varieties#prunus_domestica_belle_de_louvain" parent="prunus_domestica" itis_tsn="24774"/>
  <item-creation item="varieties#prunus_domestica_blanche_d_espagne_molle" parent="prunus_domestica" itis_tsn="24774"/>
  <item-creation item="varieties#prunus_domestica_coe_violette" parent="prunus_domestica" itis_tsn="24774"/>
  <item-creation item="varieties#prunus_domestica_datil" parent="prunus_domestica" itis_tsn="24774"/>
  <item-creation item="varieties#prunus_domestica_ente_jaune_ou_p_d_agen_blanche" parent="prunus_domestica" itis_tsn="24774"/>
  <item-creation item="varieties#prunus_domestica_floyon" parent="prunus_domestica" itis_tsn="24774"/>
  <item-creation item="varieties#prunus_domestica_genre_reine_claude_verte_tardive" parent="prunus_domestica" itis_tsn="24774"/>
  <item-creation item="varieties#prunus_domestica_goutte_d_or_de_coe" parent="prunus_domestica" itis_tsn="24774"/>
  <item-creation item="varieties#prunus_domestica_grosse_bleue_de_fin_septembre" parent="prunus_domestica" itis_tsn="24774"/>
  <item-creation item="varieties#prunus_domestica_madeleine" parent="prunus_domestica" itis_tsn="24774"/>
  <item-creation item="varieties#prunus_domestica_marcarriere_ou_datte" parent="prunus_domestica" itis_tsn="24774"/>
  <item-creation item="varieties#prunus_domestica_marie_jouveneau" parent="prunus_domestica" itis_tsn="24774"/>
  <item-creation item="varieties#prunus_domestica_mariolet" parent="prunus_domestica" itis_tsn="24774"/>
  <item-creation item="varieties#prunus_domestica_monsieur_hatif" parent="prunus_domestica" itis_tsn="24774"/>
  <item-creation item="varieties#prunus_domestica_monsieur_violet_musquette" parent="prunus_domestica" itis_tsn="24774"/>
  <item-creation item="varieties#prunus_domestica_noberte" parent="prunus_domestica" itis_tsn="24774"/>
  <item-creation item="varieties#prunus_domestica_perdrigon" parent="prunus_domestica" itis_tsn="24774"/>
  <item-creation item="varieties#prunus_domestica_prune_de_saint_antonin" parent="prunus_domestica" itis_tsn="24774"/>
  <item-creation item="varieties#prunus_domestica_reine_claude_brune" parent="prunus_domestica" itis_tsn="24774"/>
  <item-creation item="varieties#prunus_domestica_reine_claude_d_althan_conducta" parent="prunus_domestica" itis_tsn="24774"/>
  <item-creation item="varieties#prunus_domestica_reine_claude_de_bavay" parent="prunus_domestica" itis_tsn="24774"/>
  <item-creation item="varieties#prunus_domestica_reine_claude_doree" parent="prunus_domestica" itis_tsn="24774"/>
  <item-creation item="varieties#prunus_domestica_reine_claude_d_oulins" parent="prunus_domestica" itis_tsn="24774"/>
  <item-creation item="varieties#prunus_domestica_reine_claude_rouge" parent="prunus_domestica" itis_tsn="24774"/>
  <item-creation item="varieties#prunus_domestica_reine_claude_rouge_hative" parent="prunus_domestica" itis_tsn="24774"/>
  <item-creation item="varieties#prunus_domestica_reine_claude_d_oullins" parent="prunus_domestica" itis_tsn="24774"/>
  <item-creation item="varieties#prunus_domestica_saint_leonard" parent="prunus_domestica" itis_tsn="24774"/>
  <item-creation item="varieties#prunus_domestica_sainte_catherine" parent="prunus_domestica" itis_tsn="24774"/>
  <item-creation item="varieties#prunus_domestica_sanguine_de_wismes" parent="prunus_domestica" itis_tsn="24774"/>
  <item-creation item="varieties#prunus_domestica_ste_catherine" parent="prunus_domestica" itis_tsn="24774"/>
</migration>